docs/conf.py
docs/contributing.rst
docs/index.rst
docs/installation.rst
docs/_static/paper.docx
docs/_static/paper.html
docs/_static/paper.pdf
paper/Justfile
paper/README.md
paper/_quarto.yml
paper/environment.yml
paper/paper.qmd
paper/_extensions/quarto-journals/acm/ACM-Reference-Format.bst
paper/_extensions/quarto-journals/acm/_extension.yml
paper/_extensions/quarto-journals/acm/acm-sigchi-proceedings.csl
paper/_extensions/quarto-journals/acm/acmart.cls
paper/_extensions/quarto-journals/acm/acmart.dtx
paper/_extensions/quarto-journals/acm/acmarttemplate.tex
paper/_extensions/quarto-journals/acm/acmauthoryear.bbx
paper/_extensions/quarto-journals/acm/acmauthoryear.cbx
paper/_extensions/quarto-journals/acm/acmdatamodel.dbx
paper/_extensions/quarto-journals/acm/acmnumeric.bbx
paper/_extensions/quarto-journals/acm/acmnumeric.cbx
paper/_extensions/quarto-journals/acm/add-bibliography.lua
paper/_extensions/quarto-journals/acm/aft.cls
paper/_extensions/quarto-journals/acm/association-for-computing-machinery.csl
paper/_extensions/quarto-journals/acm/build-acm-authors.lua
paper/_extensions/quarto-journals/acm/color-text.lua
paper/_extensions/quarto-journals/acm/custom.scss
paper/_extensions/quarto-journals/acm/fancy-figure.lua
paper/_extensions/quarto-journals/acm/sample-franklin.png
paper/_extensions/quarto-journals/acm/shortcodes.lua
paper/_extensions/quarto-journals/acm/te.bst
paper/_extensions/quarto-journals/acm/partials/_acmart_abstract.tex
paper/_extensions/quarto-journals/acm/partials/_acmart_authors.tex
paper/_extensions/quarto-journals/acm/partials/_acmart_preamble.tex
paper/_extensions/quarto-journals/acm/partials/title.tex
paper/support/acm-proceedings.csl
paper/support/main.bib
soft_search/__init__.py
soft_search/constants.py
soft_search/metrics.py
soft_search/nsf.py
soft_search/py.typed
soft_search/seed.py
soft_search/bin/__init__.py
soft_search/bin/find_nsf_award_ids_in_github_readmes_and_link.py
soft_search/bin/fit_and_eval_all_models.py
soft_search-0.7.0.dist-info/LICENSE
soft_search-0.7.0.dist-info/METADATA
soft_search-0.7.0.dist-info/WHEEL
soft_search-0.7.0.dist-info/entry_points.txt
soft_search-0.7.0.dist-info/top_level.txt
soft_search-0.7.0.dist-info/RECORD
