Metadata-Version: 2.1
Name: soft-search
Version: 0.7.0
Summary: searching for software promises in grant applications
Author-email: Eva Maxfield Brown <evamxb@uw.edu>, Nic Weber <nmweber@uw.edu>, Lindsey Schwartz <lsschwar@uw.edu>, Richard Lewei Huang <lwhuang@uw.edu>
License: MIT License
Project-URL: Homepage, https://github.com/si2-urssi/eager
Project-URL: Bug Tracker, https://github.com/si2-urssi/eager/issues
Project-URL: Documentation, https://si2-urssi.github.io/eager
Project-URL: User Support, https://github.com/si2-urssi/eager/issues
Classifier: Development Status :: 4 - Beta
Classifier: Natural Language :: English
Classifier: Programming Language :: Python :: 3.8
Classifier: Programming Language :: Python :: 3.9
Classifier: Programming Language :: Python :: 3.10
Requires-Python: >=3.8
License-File: LICENSE
Requires-Dist: beautifulsoup4 (~=4.11)
Requires-Dist: dataclasses-json (~=0.5)
Requires-Dist: datasets (~=2.0)
Requires-Dist: embetter[sentence-tfm] (~=0.3.1)
Requires-Dist: ghapi (~=1.0)
Requires-Dist: pandas (~=1.4)
Requires-Dist: pyarrow (~=9.0)
Requires-Dist: python-dotenv (~=0.21)
Requires-Dist: requests (~=2.28)
Requires-Dist: scikit-learn (~=1.1)
Requires-Dist: statsmodels (~=0.13.2)
Requires-Dist: torch (~=1.12)
Requires-Dist: tqdm (~=4.64)
Requires-Dist: transformers (~=4.21)
Provides-Extra: dev
Requires-Dist: ipython (>=8.4.0) ; extra == 'dev'
Requires-Dist: matplotlib (>=3.5.2) ; extra == 'dev'
Provides-Extra: docs
Requires-Dist: m2r2 (>=0.2.7) ; extra == 'docs'
Requires-Dist: Sphinx (>=4.0.0) ; extra == 'docs'
Requires-Dist: furo (>=2022.4.7) ; extra == 'docs'
Requires-Dist: numpydoc ; extra == 'docs'
Requires-Dist: sphinx-copybutton ; extra == 'docs'
Requires-Dist: docutils (<0.19,>=0.18) ; extra == 'docs'
Provides-Extra: lint
Requires-Dist: black (>=22.3.0) ; extra == 'lint'
Requires-Dist: check-manifest (>=0.48) ; extra == 'lint'
Requires-Dist: ruff (>=0.0.216) ; extra == 'lint'
Requires-Dist: mypy (>=0.790) ; extra == 'lint'
Requires-Dist: pre-commit (>=2.20.0) ; extra == 'lint'
Requires-Dist: types-requests (~=2.28) ; extra == 'lint'
Provides-Extra: test
Requires-Dist: coverage (>=5.1) ; extra == 'test'
Requires-Dist: pytest (>=5.4.3) ; extra == 'test'
Requires-Dist: pytest-cov (>=2.9.0) ; extra == 'test'
Requires-Dist: pytest-raises (>=0.11) ; extra == 'test'
